x16cli/__init__.py
x16cli/actions.py
x16cli/checks.py
x16cli/config.py
x16cli-0.1.1.data/scripts/x16
x16cli-0.1.1.dist-info/LICENSE
x16cli-0.1.1.dist-info/METADATA
x16cli-0.1.1.dist-info/WHEEL
x16cli-0.1.1.dist-info/top_level.txt
x16cli-0.1.1.dist-info/RECORD
